deephaven/plugin/utilities/__init__.py
deephaven/plugin/utilities/dhe_safe_callback_wrapper.py
deephaven/plugin/utilities/utils.py
deephaven_plugin_utilities-0.0.2.dist-info/LICENSE
deephaven_plugin_utilities-0.0.2.dist-info/METADATA
deephaven_plugin_utilities-0.0.2.dist-info/WHEEL
deephaven_plugin_utilities-0.0.2.dist-info/top_level.txt
deephaven_plugin_utilities-0.0.2.dist-info/RECORD
