Metadata-Version: 2.1
Name: deephaven-plugin-utilities
Version: 0.0.2
Summary: Deephaven Plugin Utilities
Home-page: https://github.com/deephaven/deephaven-plugins
Author: Joe Numainville
Author-email: josephnumainville@deephaven.io
Project-URL: Source Code, https://github.com/deephaven/deephaven-plugins
Project-URL: Bug Tracker, https://github.com/deephaven/deephaven-plugins/issues
Keywords: deephaven,plugin,utilities
Platform: any
Classifier: Programming Language :: Python :: 3
Classifier: License :: OSI Approved :: Apache Software License
Classifier: Operating System :: OS Independent
Classifier: Environment :: Plugins
Classifier: Development Status :: 3 - Alpha
License-File: LICENSE
Requires-Dist: deephaven-plugin>=0.6.0
